widecity_image_downloader/Image.py
widecity_image_downloader/__init__.py
widecity_image_downloader-0.0.5.dist-info/LICENSE
widecity_image_downloader-0.0.5.dist-info/METADATA
widecity_image_downloader-0.0.5.dist-info/WHEEL
widecity_image_downloader-0.0.5.dist-info/top_level.txt
widecity_image_downloader-0.0.5.dist-info/RECORD
