Metadata-Version: 2.1
Name: widecity-image-downloader
Version: 0.0.5
Summary: a simple package to download images from internet based on the keywords provided.
Home-page: https://github.com/pypa/sampleproject
Author: Example Author
Author-email: widecity.official@gmail.com
Project-URL: Bug Tracker, https://github.com/pypa/sampleproject/issues
Classifier: Programming Language :: Python :: 3
Classifier: License :: OSI Approved :: MIT License
Classifier: Operating System :: OS Independent
Requires-Python: >=3.7
License-File: LICENSE
